{"label": "normal_detailed", "logs": [{"location": "q1", "timestamp": "2024-01-01T10:00:01.781Z", "activity_text": "Test Started"}, {"location": "q1", "timestamp": "2024-01-01T10:00:03.684Z", "activity_text": "Selected question 0"}, {"location": "q1", "timestamp": "2024-01-01T10:00:59.107Z", "activity_text": "Selected option 1 for question 0"}, {"location": "q1", "timestamp": "2024-01-01T10:01:05.502Z", "activity_text": "Cleared option for question 0"}, {"location": "q1", "timestamp": "2024-01-01T10:01:08.767Z", "activity_text": "Selected option 0 for question 0"}, {"location": "q2", "timestamp": "2024-01-01T10:01:10.033Z", "activity_text": "Selected question 1"}, {"location": "q2", "timestamp": "2024-01-01T10:02:08.040Z", "activity_text": "Selected option 0 for question 1"}, {"location": "q2", "timestamp": "2024-01-01T10:02:09.040Z", "activity_text": "Cleared option for question 1"}, {"location": "q2", "timestamp": "2024-01-01T10:02:10.040Z", "activity_text": "Selected option 2 for question 1"}, {"location": "q3", "timestamp": "2024-01-01T10:02:11.612Z", "activity_text": "Selected question 2"}, {"location": "q3", "timestamp": "2024-01-01T10:03:06.763Z", "activity_text": "Selected option 2 for question 2"}, {"location": "q4", "timestamp": "2024-01-01T10:03:07.780Z", "activity_text": "Selected question 3"}, {"location": "q4", "timestamp": "2024-01-01T10:04:10.149Z", "activity_text": "Selected option 0 for question 3"}, {"location": "q3", "timestamp": "2024-01-01T10:04:11.149Z", "activity_text": "Selected question 2"}, {"location": "q5", "timestamp": "2024-01-01T10:04:13.063Z", "activity_text": "Selected question 4"}, {"location": "q5", "timestamp": "2024-01-01T10:05:05.275Z", "activity_text": "Selected option 3 for question 4"}, {"location": "q6", "timestamp": "2024-01-01T10:05:06.275Z", "activity_text": "Selected question 5"}, {"location": "q6", "timestamp": "2024-01-01T10:06:35.480Z", "activity_text": "Selected option 2 for question 5"}, {"location": "q11", "timestamp": "2024-01-01T10:06:37.475Z", "activity_text": "Selected question 10"}, {"location": "q11", "timestamp": "2024-01-01T10:07:11.384Z", "activity_text": "Selected option 2 for question 10"}, {"location": "q11", "timestamp": "2024-01-01T10:07:21.110Z", "activity_text": "Cleared option for question 10"}, {"location": "q11", "timestamp": "2024-01-01T10:07:28.979Z", "activity_text": "Selected option 1 for question 10"}, {"location": "q12", "timestamp": "2024-01-01T10:07:30.711Z", "activity_text": "Selected question 11"}, {"location": "q12", "timestamp": "2024-01-01T10:08:05.389Z", "activity_text": "Selected option 3 for question 11"}, {"location": "q13", "timestamp": "2024-01-01T10:08:06.571Z", "activity_text": "Selected question 12"}, {"location": "q13", "timestamp": "2024-01-01T10:08:36.912Z", "activity_text": "Selected option 1 for question 12"}, {"location": "q14", "timestamp": "2024-01-01T10:08:38.491Z", "activity_text": "Selected question 13"}, {"location": "q14", "timestamp": "2024-01-01T10:09:49.114Z", "activity_text": "Selected option 2 for question 13"}, {"location": "q29", "timestamp": "2024-01-01T10:09:50.114Z", "activity_text": "Selected question 28"}, {"location": "q29", "timestamp": "2024-01-01T10:13:41.980Z", "activity_text": "Selected option 3 for question 28"}, {"location": "q30", "timestamp": "2024-01-01T10:13:44.054Z", "activity_text": "Selected question 29"}, {"location": "q30", "timestamp": "2024-01-01T10:18:52.001Z", "activity_text": "Selected option 2 for question 29"}, {"location": "q7", "timestamp": "2024-01-01T10:18:53.001Z", "activity_text": "Selected question 6"}, {"location": "q7", "timestamp": "2024-01-01T10:19:37.715Z", "activity_text": "Selected option 1 for question 6"}, {"location": "q4", "timestamp": "2024-01-01T10:19:38.880Z", "activity_text": "Selected question 3"}, {"location": "q20", "timestamp": "2024-01-01T10:19:41.599Z", "activity_text": "Selected question 19"}, {"location": "q20", "timestamp": "2024-01-01T10:22:51.216Z", "activity_text": "Selected option 1 for question 19"}, {"location": "q21", "timestamp": "2024-01-01T10:22:53.858Z", "activity_text": "Selected question 20"}, {"location": "q21", "timestamp": "2024-01-01T10:23:29.801Z", "activity_text": "Selected option 2 for question 20"}, {"location": "q24", "timestamp": "2024-01-01T10:23:30.801Z", "activity_text": "Selected question 23"}, {"location": "q24", "timestamp": "2024-01-01T10:25:33.381Z", "activity_text": "Selected option 0 for question 23"}, {"location": "q24", "timestamp": "2024-01-01T10:25:48.228Z", "activity_text": "Cleared option for question 23"}, {"location": "q24", "timestamp": "2024-01-01T10:25:51.221Z", "activity_text": "Selected option 2 for question 23"}, {"location": "q25", "timestamp": "2024-01-01T10:25:53.100Z", "activity_text": "Selected question 24"}, {"location": "q25", "timestamp": "2024-01-01T10:27:33.390Z", "activity_text": "Selected option 0 for question 24"}, {"location": "q25", "timestamp": "2024-01-01T10:27:43.821Z", "activity_text": "Cleared option for question 24"}, {"location": "q25", "timestamp": "2024-01-01T10:27:50.966Z", "activity_text": "Selected option 2 for question 24"}, {"location": "q27", "timestamp": "2024-01-01T10:27:51.966Z", "activity_text": "Selected question 26"}, {"location": "q27", "timestamp": "2024-01-01T10:29:15.770Z", "activity_text": "Selected option 3 for question 26"}, {"location": "q27", "timestamp": "2024-01-01T10:29:32.589Z", "activity_text": "Cleared option for question 26"}, {"location": "q27", "timestamp": "2024-01-01T10:29:35.527Z", "activity_text": "Selected option 0 for question 26"}, {"location": "q28", "timestamp": "2024-01-01T10:29:36.859Z", "activity_text": "Selected question 27"}, {"location": "q28", "timestamp": "2024-01-01T10:30:10.595Z", "activity_text": "Selected option 1 for question 27"}, {"location": "q8", "timestamp": "2024-01-01T10:30:12.051Z", "activity_text": "Selected question 7"}, {"location": "q8", "timestamp": "2024-01-01T10:34:18.959Z", "activity_text": "Selected option 1 for question 7"}, {"location": "q8", "timestamp": "2024-01-01T10:34:26.783Z", "activity_text": "Cleared option for question 7"}, {"location": "q8", "timestamp": "2024-01-01T10:34:31.277Z", "activity_text": "Selected option 1 for question 7"}, {"location": "q9", "timestamp": "2024-01-01T10:34:32.639Z", "activity_text": "Selected question 8"}, {"location": "q9", "timestamp": "2024-01-01T10:38:24.537Z", "activity_text": "Selected option 1 for question 8"}, {"location": "q9", "timestamp": "2024-01-01T10:38:34.655Z", "activity_text": "Cleared option for question 8"}, {"location": "q9", "timestamp": "2024-01-01T10:38:38.990Z", "activity_text": "Selected option 1 for question 8"}, {"location": "q9", "timestamp": "2024-01-01T10:38:39.990Z", "activity_text": "Submitted Test"}]}