{"label": "normal_detailed", "logs": [{"location": "q1", "timestamp": "2024-01-01T10:00:01.491Z", "activity_text": "Test Started"}, {"location": "q1", "timestamp": "2024-01-01T10:00:03.219Z", "activity_text": "Selected question 0"}, {"location": "q1", "timestamp": "2024-01-01T10:01:08.802Z", "activity_text": "Selected option 0 for question 0"}, {"location": "q2", "timestamp": "2024-01-01T10:01:10.715Z", "activity_text": "Selected question 1"}, {"location": "q2", "timestamp": "2024-01-01T10:02:05.584Z", "activity_text": "Selected option 0 for question 1"}, {"location": "q3", "timestamp": "2024-01-01T10:02:07.167Z", "activity_text": "Selected question 2"}, {"location": "q3", "timestamp": "2024-01-01T10:02:51.116Z", "activity_text": "Selected option 0 for question 2"}, {"location": "q4", "timestamp": "2024-01-01T10:02:52.116Z", "activity_text": "Selected question 3"}, {"location": "q4", "timestamp": "2024-01-01T10:04:05.981Z", "activity_text": "Selected option 0 for question 3"}, {"location": "q10", "timestamp": "2024-01-01T10:04:07.893Z", "activity_text": "Selected question 9"}, {"location": "q10", "timestamp": "2024-01-01T10:07:14.492Z", "activity_text": "Selected option 1 for question 9"}, {"location": "q11", "timestamp": "2024-01-01T10:07:16.136Z", "activity_text": "Selected question 10"}, {"location": "q11", "timestamp": "2024-01-01T10:08:28.996Z", "activity_text": "Selected option 1 for question 10"}, {"location": "q11", "timestamp": "2024-01-01T10:08:42.783Z", "activity_text": "Cleared option for question 10"}, {"location": "q11", "timestamp": "2024-01-01T10:08:45.557Z", "activity_text": "Selected option 1 for question 10"}, {"location": "q12", "timestamp": "2024-01-01T10:08:47.044Z", "activity_text": "Selected question 11"}, {"location": "q12", "timestamp": "2024-01-01T10:09:48.042Z", "activity_text": "Selected option 3 for question 11"}, {"location": "q13", "timestamp": "2024-01-01T10:09:49.086Z", "activity_text": "Selected question 12"}, {"location": "q13", "timestamp": "2024-01-01T10:10:38.721Z", "activity_text": "Selected option 1 for question 12"}, {"location": "q14", "timestamp": "2024-01-01T10:10:39.721Z", "activity_text": "Selected question 13"}, {"location": "q14", "timestamp": "2024-01-01T10:12:05.763Z", "activity_text": "Selected option 0 for question 13"}, {"location": "q29", "timestamp": "2024-01-01T10:12:07.307Z", "activity_text": "Selected question 28"}, {"location": "q29", "timestamp": "2024-01-01T10:15:35.199Z", "activity_text": "Selected option 3 for question 28"}, {"location": "q30", "timestamp": "2024-01-01T10:15:36.477Z", "activity_text": "Selected question 29"}, {"location": "q30", "timestamp": "2024-01-01T10:18:24.551Z", "activity_text": "Selected option 0 for question 29"}, {"location": "q5", "timestamp": "2024-01-01T10:18:26.987Z", "activity_text": "Selected question 4"}, {"location": "q5", "timestamp": "2024-01-01T10:19:56.800Z", "activity_text": "Selected option 2 for question 4"}, {"location": "q6", "timestamp": "2024-01-01T10:19:58.882Z", "activity_text": "Selected question 5"}, {"location": "q6", "timestamp": "2024-01-01T10:21:22.324Z", "activity_text": "Selected option 1 for question 5"}, {"location": "q7", "timestamp": "2024-01-01T10:21:23.324Z", "activity_text": "Selected question 6"}, {"location": "q7", "timestamp": "2024-01-01T10:23:09.761Z", "activity_text": "Selected option 3 for question 6"}, {"location": "q17", "timestamp": "2024-01-01T10:23:11.155Z", "activity_text": "Selected question 16"}, {"location": "q17", "timestamp": "2024-01-01T10:24:25.124Z", "activity_text": "Selected option 2 for question 16"}, {"location": "q18", "timestamp": "2024-01-01T10:24:26.124Z", "activity_text": "Selected question 17"}, {"location": "q18", "timestamp": "2024-01-01T10:27:27.867Z", "activity_text": "Selected option 1 for question 17"}, {"location": "q24", "timestamp": "2024-01-01T10:27:28.867Z", "activity_text": "Selected question 23"}, {"location": "q24", "timestamp": "2024-01-01T10:29:06.888Z", "activity_text": "Selected option 1 for question 23"}, {"location": "q10", "timestamp": "2024-01-01T10:29:08.234Z", "activity_text": "Selected question 9"}, {"location": "q15", "timestamp": "2024-01-01T10:29:09.575Z", "activity_text": "Selected question 14"}, {"location": "q15", "timestamp": "2024-01-01T10:30:57.676Z", "activity_text": "Selected option 1 for question 14"}, {"location": "q16", "timestamp": "2024-01-01T10:30:58.795Z", "activity_text": "Selected question 15"}, {"location": "q16", "timestamp": "2024-01-01T10:32:23.096Z", "activity_text": "Selected option 1 for question 15"}, {"location": "q19", "timestamp": "2024-01-01T10:32:25.280Z", "activity_text": "Selected question 18"}, {"location": "q19", "timestamp": "2024-01-01T10:35:32.354Z", "activity_text": "Selected option 3 for question 18"}, {"location": "q20", "timestamp": "2024-01-01T10:35:33.698Z", "activity_text": "Selected question 19"}, {"location": "q20", "timestamp": "2024-01-01T10:38:51.416Z", "activity_text": "Selected option 1 for question 19"}, {"location": "q21", "timestamp": "2024-01-01T10:38:53.660Z", "activity_text": "Selected question 20"}, {"location": "q21", "timestamp": "2024-01-01T10:40:00.227Z", "activity_text": "Selected option 2 for question 20"}, {"location": "q22", "timestamp": "2024-01-01T10:40:02.818Z", "activity_text": "Selected question 21"}, {"location": "q22", "timestamp": "2024-01-01T10:41:11.073Z", "activity_text": "Selected option 1 for question 21"}, {"location": "q23", "timestamp": "2024-01-01T10:41:12.657Z", "activity_text": "Selected question 22"}, {"location": "q23", "timestamp": "2024-01-01T10:42:01.675Z", "activity_text": "Selected option 2 for question 22"}, {"location": "q25", "timestamp": "2024-01-01T10:42:02.675Z", "activity_text": "Selected question 24"}, {"location": "q25", "timestamp": "2024-01-01T10:43:31.704Z", "activity_text": "Selected option 2 for question 24"}, {"location": "q28", "timestamp": "2024-01-01T10:43:32.704Z", "activity_text": "Selected question 27"}, {"location": "q28", "timestamp": "2024-01-01T10:45:56.379Z", "activity_text": "Selected option 2 for question 27"}, {"location": "q8", "timestamp": "2024-01-01T10:45:57.634Z", "activity_text": "Selected question 7"}, {"location": "q8", "timestamp": "2024-01-01T10:48:42.914Z", "activity_text": "Selected option 0 for question 7"}, {"location": "q9", "timestamp": "2024-01-01T10:48:44.247Z", "activity_text": "Selected question 8"}, {"location": "q9", "timestamp": "2024-01-01T10:51:45.796Z", "activity_text": "Selected option 0 for question 8"}, {"location": "q26", "timestamp": "2024-01-01T10:51:47.619Z", "activity_text": "Selected question 25"}, {"location": "q26", "timestamp": "2024-01-01T10:53:39.500Z", "activity_text": "Selected option 0 for question 25"}, {"location": "q27", "timestamp": "2024-01-01T10:53:41.336Z", "activity_text": "Selected question 26"}, {"location": "q27", "timestamp": "2024-01-01T10:55:08.907Z", "activity_text": "Selected option 0 for question 26"}, {"location": "q27", "timestamp": "2024-01-01T10:55:10.377Z", "activity_text": "Submitted Test"}]}